{
    "2.0.0": {
        "md5": "24c452ac732f80504bb6dd0ff9e452e1",
        "version": "0.2.388",
        "filename": "revvy_firmware-0.2.388.bin",
        "length": 114888
    },
    "1.0.0": {
        "md5": "7b6962bb27d440b4cc160a8828097349",
        "version": "0.1.336",
        "filename": "revvy_firmware-0.1.336.bin",
        "length": 107896
    },
    "1.0.1": {
        "md5": "7b6962bb27d440b4cc160a8828097349",
        "version": "0.1.336",
        "filename": "revvy_firmware-0.1.336.bin",
        "length": 107896
    }
}